librelingo_json_export/__init__.py
librelingo_json_export/challenge_types.py
librelingo_json_export/challenges.py
librelingo_json_export/cli.py
librelingo_json_export/course.py
librelingo_json_export/dictionary.py
librelingo_json_export/export.py
librelingo_json_export/module.py
librelingo_json_export/settings.py
librelingo_json_export/skills.py
librelingo_json_export-0.11.0.dist-info/METADATA
librelingo_json_export-0.11.0.dist-info/WHEEL
librelingo_json_export-0.11.0.dist-info/entry_points.txt
librelingo_json_export-0.11.0.dist-info/RECORD
