Metadata-Version: 2.1
Name: librelingo-json-export
Version: 0.11.0
Summary: Export LibreLingo courses in the JSON format used by the web app
License: AGPLv3
Author: Dániel Kántor
Author-email: git@daniel-kantor.com
Requires-Python: >=3.8,<4.0
Classifier: License :: Other/Proprietary License
Classifier: Programming Language :: Python :: 3
Classifier: Programming Language :: Python :: 3.8
Classifier: Programming Language :: Python :: 3.9
Classifier: Programming Language :: Python :: 3.10
Classifier: Programming Language :: Python :: 3.11
Provides-Extra: hunspell
Requires-Dist: click (>=7.0.0,<8.0.0)
Requires-Dist: editdistance (>=0.6.0,<0.7.0)
Requires-Dist: hunspell (>=0.5.5,<0.6.0) ; extra == "hunspell"
Requires-Dist: librelingo-types (>=3.0.0,<4.0.0)
Requires-Dist: librelingo-utils (>=2.6.2,<3.0.0)
Requires-Dist: librelingo-yaml-loader (>=1.12.0,<2.0.0)
Requires-Dist: python-slugify (>=8.0.0,<9.0.0)
